Metadata-Version: 2.3
Name: swarmauri_tool_jupyterfromdict
Version: 0.7.5
Summary: A tool that converts a plain dictionary into a NotebookNode object using nbformat, facilitating programmatic notebook creation.
License: Apache-2.0
Author: Jacob Stewart
Author-email: jacob@swarmauri.com
Requires-Python: >=3.10,<3.13
Classifier: License :: OSI Approved :: Apache Software License
Classifier: Programming Language :: Python :: 3.10
Classifier: Programming Language :: Python :: 3.11
Classifier: Programming Language :: Python :: 3.12
Classifier: Programming Language :: Python :: 3.13
Requires-Dist: nbformat (>=5.10.4)
Requires-Dist: swarmauri_base
Requires-Dist: swarmauri_core
Requires-Dist: swarmauri_standard
